qrew/Qrew.py
qrew/Qrew_api_helper.py
qrew/Qrew_button.py
qrew/Qrew_common.py
qrew/Qrew_dialogs.py
qrew/Qrew_filedialog.py
qrew/Qrew_find_vlc.py
qrew/Qrew_measurement_metrics.py
qrew/Qrew_message_handlers.py
qrew/Qrew_messagebox.py
qrew/Qrew_micwidget_icons.py
qrew/Qrew_resources.py
qrew/Qrew_settings.py
qrew/Qrew_styles.py
qrew/Qrew_thread_utils.py
qrew/Qrew_vlc_helper_v2.py
qrew/Qrew_vlc_widget.py
qrew/Qrew_workers_v2.py
qrew/__init__.py
qrew/__main__.py
qrew/main.py
qrew/settings.json
qrew/version.py
qrew-1.0.1.dist-info/licenses/LICENSE
qrew-1.0.1.dist-info/METADATA
qrew-1.0.1.dist-info/WHEEL
qrew-1.0.1.dist-info/entry_points.txt
qrew-1.0.1.dist-info/top_level.txt
qrew-1.0.1.dist-info/RECORD
