Metadata-Version: 2.4
Name: qrew
Version: 1.0.1
Summary: Automated loudspeaker measurement system using REW API
Author: Juan F. Loya, MD
License: GPL-3.0-or-later
Project-URL: Homepage, https://github.com/docdude/Qrew
Project-URL: Issues, https://github.com/docdude/Qrew/issues
Project-URL: Repository, https://github.com/docdude/Qrew.git
Classifier: Development Status :: 4 - Beta
Classifier: Intended Audience :: Science/Research
Classifier: Operating System :: OS Independent
Classifier: Programming Language :: Python :: 3
Classifier: Programming Language :: Python :: 3.8
Classifier: Programming Language :: Python :: 3.9
Classifier: Programming Language :: Python :: 3.10
Classifier: Programming Language :: Python :: 3.11
Classifier: Programming Language :: Python :: 3.12
Classifier: Programming Language :: Python :: 3.13
Classifier: Topic :: Scientific/Engineering :: Physics
Requires-Python: >=3.8
License-File: LICENSE
Requires-Dist: PyQt5>=5.15.0
Requires-Dist: requests>=2.25.0
Requires-Dist: flask>=2.0.0
Requires-Dist: numpy>=1.19.0
Requires-Dist: pandas>=1.2.0
Requires-Dist: colour>=0.1.5
Requires-Dist: gevent>=22.10.2
Requires-Dist: pyobjc>=7.0.0; platform_system == "Darwin"
Requires-Dist: python-vlc>=3.0.0; platform_system != "Windows"
Requires-Dist: python-vlc>=3.0.0; platform_system == "Windows"
Provides-Extra: dev
Requires-Dist: pytest>=6.0; extra == "dev"
Requires-Dist: pytest-qt>=4.0; extra == "dev"
Requires-Dist: black>=22.0; extra == "dev"
Requires-Dist: flake8>=4.0; extra == "dev"
Dynamic: license-file
